shy_sh/agents/__init__.py
shy_sh/agents/chains/__init__.py
shy_sh/agents/chains/alternative_commands.py
shy_sh/agents/chains/explain.py
shy_sh/agents/chains/python_expert.py
shy_sh/agents/chains/shell_expert.py
shy_sh/agents/chains/shy_agent.py
shy_sh/agents/llms.py
shy_sh/agents/misc.py
shy_sh/agents/shy_agent/__init__.py
shy_sh/agents/shy_agent/agent.py
shy_sh/agents/shy_agent/audio.py
shy_sh/agents/shy_agent/edges/__init__.py
shy_sh/agents/shy_agent/edges/final_response.py
shy_sh/agents/shy_agent/edges/tool_calls.py
shy_sh/agents/shy_agent/graph.py
shy_sh/agents/shy_agent/nodes/__init__.py
shy_sh/agents/shy_agent/nodes/chatbot.py
shy_sh/agents/shy_agent/nodes/tools_handler.py
shy_sh/agents/tools/__init__.py
shy_sh/agents/tools/python_expert.py
shy_sh/agents/tools/shell.py
shy_sh/agents/tools/shell_exe.py
shy_sh/agents/tools/shell_expert.py
shy_sh/agents/tools/shell_history.py
shy_sh/main.py
shy_sh/manager/chat_manager.py
shy_sh/manager/history.py
shy_sh/manager/sql_models.py
shy_sh/models.py
shy_sh/settings.py
shy_sh/utils.py
shy_sh-1.3.4.dist-info/METADATA
shy_sh-1.3.4.dist-info/WHEEL
shy_sh-1.3.4.dist-info/entry_points.txt
shy_sh-1.3.4.dist-info/RECORD
