Metadata-Version: 2.1
Name: shy_sh
Version: 1.3.4
Summary: Shell copilot - sh shell AI copilot
Home-page: https://github.com/mceck/shy-sh
License: MIT
Author: Mattia Cecchini
Author-email: matcecco@gmail.com
Requires-Python: >=3.10,<3.14
Classifier: License :: OSI Approved :: MIT License
Classifier: Programming Language :: Python :: 3
Classifier: Programming Language :: Python :: 3.10
Classifier: Programming Language :: Python :: 3.11
Classifier: Programming Language :: Python :: 3.12
Classifier: Programming Language :: Python :: 3.13
Classifier: Topic :: Scientific/Engineering :: Artificial Intelligence
Classifier: Topic :: Terminals
Classifier: Topic :: Utilities
Provides-Extra: audio
Provides-Extra: aws
Requires-Dist: langchain (>=0.3.20,<0.4.0)
Requires-Dist: langchain-anthropic (>=0.3.9,<0.4.0)
Requires-Dist: langchain-aws (>=0.2.15,<0.3.0) ; extra == "aws"
Requires-Dist: langchain-google-genai (>=2.0.11,<3.0.0)
Requires-Dist: langchain-groq (>=0.3.8,<0.4.0)
Requires-Dist: langchain-ollama (>=0.3.8,<0.4.0)
Requires-Dist: langchain-openai (>=0.3.8,<0.4.0)
Requires-Dist: langgraph (==0.6.7)
Requires-Dist: pydantic-settings (>=2.8.1,<3.0.0)
Requires-Dist: pyperclip (>=1.9.0,<2.0.0)
Requires-Dist: pyreadline3 (>=3.5.4,<4.0.0) ; sys_platform == "win32"
Requires-Dist: pyyaml (>=6.0.2,<7.0.0)
Requires-Dist: questionary (>=2.1.0,<3.0.0)
Requires-Dist: speechrecognition (>=3.14.1,<4.0.0) ; extra == "audio"
Requires-Dist: tiktoken (>=0.11.0,<0.12.0)
Requires-Dist: typer (>=0.17.4,<0.18.0)
Requires-Dist: tzlocal (>=5.3.1,<6.0.0)
Project-URL: Repository, https://github.com/mceck/shy-sh
